mets_dnx/__init__.py
mets_dnx/factory.py
mets_dnx-0.1.18.dist-info/LICENSE.txt
mets_dnx-0.1.18.dist-info/METADATA
mets_dnx-0.1.18.dist-info/WHEEL
mets_dnx-0.1.18.dist-info/top_level.txt
mets_dnx-0.1.18.dist-info/RECORD
